promail/__init__.py
promail/clients/__init__.py
promail/clients/aws.py
promail/clients/email_manager.py
promail/clients/gmail.py
promail/clients/imap_client.py
promail/clients/microsoft.py
promail/clients/py.typed
promail/clients/smtp_client.py
promail/core/__init__.py
promail/core/attachments/__init__.py
promail/core/attachments/attachments.py
promail/core/embedded_attachments.py
promail/core/messages/__init__.py
promail/core/messages/messages.py
promail/filters/__init__.py
promail/filters/email_filter.py
promail/filters/gmail_filter.py
promail/filters/imap_filter.py
promail-0.9.0.dist-info/LICENSE
promail-0.9.0.dist-info/WHEEL
promail-0.9.0.dist-info/METADATA
promail-0.9.0.dist-info/RECORD
