Metadata-Version: 2.1
Name: promail
Version: 0.9.0
Summary: Promail: The Python Email Automation Framework
Home-page: https://github.com/trafire/promail
License: GNU
Keywords: promail,email,automation
Author: Antoine Wood
Author-email: antoinewood@gmail.com
Requires-Python: >=3.8,<4.0
Classifier: License :: Other/Proprietary License
Classifier: Programming Language :: Python :: 3
Classifier: Programming Language :: Python :: 3.10
Classifier: Programming Language :: Python :: 3.8
Classifier: Programming Language :: Python :: 3.9
Requires-Dist: Faker (>=13.15.1,<14.0.0)
Requires-Dist: IMAPClient (>=2.3.1,<3.0.0)
Requires-Dist: boto3 (>=1.24.46,<2.0.0)
Requires-Dist: boto3-stubs (>=1.24.46,<2.0.0)
Requires-Dist: docformatter (>=1.4,<2.0)
Requires-Dist: email-validator (>=1.2.1,<2.0.0)
Requires-Dist: google-api-core (>=2.8.0,<3.0.0)
Requires-Dist: google-api-python-client (>=2.47.0,<3.0.0)
Requires-Dist: google-auth (>=2.6.6,<3.0.0)
Requires-Dist: google-auth-httplib2 (>=0.1.0,<0.2.0)
Requires-Dist: google-auth-oauthlib (>=0.5.1,<0.6.0)
Requires-Dist: importlib-metadata (>=4.11.3,<5.0.0); python_version < "3.8"
Requires-Dist: nox (>=2022.1.7,<2023.0.0)
Requires-Dist: pydantic (>=1.9.1,<2.0.0)
Requires-Dist: pyment (>=0.3.3,<0.4.0)
Requires-Dist: python-dotenv (>=0.1.0,<0.2.0)
Requires-Dist: requests (>=2.27.1,<3.0.0)
Requires-Dist: tabulate (>=0.8.9,<0.9.0)
Project-URL: Documentation, https://promail.readthedocs.io
Project-URL: Repository, https://github.com/trafire/promail
